setup.py
expressdb/__init__.py
expressdb/collection.py
expressdb/database.py
expressdb/helpers.py
expressdb.egg-info/PKG-INFO
expressdb.egg-info/SOURCES.txt
expressdb.egg-info/dependency_links.txt
expressdb.egg-info/requires.txt
expressdb.egg-info/top_level.txt